resector/BrainAnatomyLabelsV3_0.txt
resector/__init__.py
resector/image.py
resector/io.py
resector/mesh.py
resector/parcellation.py
resector/random_resection.py
resector/resector.py
resector/shape.py
resector/texture.py
resector/timer.py
resector/cli/__init__.py
resector/cli/create_noise_volume.py
resector/cli/resect.py
resector/resources/geodesic_polyhedron.vtp
resector/resources/volumes.csv
resector-0.2.10.dist-info/LICENSE
resector-0.2.10.dist-info/METADATA
resector-0.2.10.dist-info/WHEEL
resector-0.2.10.dist-info/entry_points.txt
resector-0.2.10.dist-info/top_level.txt
resector-0.2.10.dist-info/RECORD
