Metadata-Version: 2.1
Name: resector
Version: 0.2.10
Summary: Algorithm to simulate resections osurgery on brain MRI scans.
Home-page: https://github.com/fepegar/resector
Author: Fernando Perez-Garcia
Author-email: fernando.perezgarcia.17@ucl.ac.uk
License: MIT license
Keywords: resector
Classifier: Development Status :: 2 - Pre-Alpha
Classifier: Intended Audience :: Developers
Classifier: License :: OSI Approved :: MIT License
Classifier: Natural Language :: English
Classifier: Programming Language :: Python :: 3
Classifier: Programming Language :: Python :: 3.6
Classifier: Programming Language :: Python :: 3.7
Classifier: Programming Language :: Python :: 3.8
Classifier: Programming Language :: Python :: 3.9
Classifier: Programming Language :: Python :: 3.10
Requires-Python: >=3.6
License-File: LICENSE
Requires-Dist: Click (>=7.0)
Requires-Dist: noise
Requires-Dist: torchio
Requires-Dist: SimpleITK
Requires-Dist: scikit-image
Requires-Dist: scipy
Requires-Dist: vtk
